comid/OLdconvoflow.py
comid/__init__.py
comid/collector.py
comid/convobridge.py
comid/convoflow.py
comid/explorer.py
comid/pullpush.py
comid-0.0.4.dist-info/LICENSE
comid-0.0.4.dist-info/METADATA
comid-0.0.4.dist-info/WHEEL
comid-0.0.4.dist-info/top_level.txt
comid-0.0.4.dist-info/RECORD
