Metadata-Version: 2.2
Name: comid
Version: 0.0.4
Summary: A community identification module for Reddit conversations
Home-page: https://github.com/d0d0th/comid
Author: Thiago Henrique dos Santos
Author-email: a22100011@alunos.ulht.pt
License: MIT License
Classifier: Development Status :: 3 - Alpha
Classifier: Programming Language :: Python :: 3 :: Only
Classifier: Programming Language :: Python :: 3.10
Classifier: Programming Language :: Python :: 3.11
Classifier: Programming Language :: Python :: 3.12
Classifier: Intended Audience :: Developers
Classifier: Topic :: Utilities
Classifier: License :: OSI Approved :: MIT License
Classifier: Operating System :: OS Independent
Requires-Python: >=3.10
License-File: LICENSE
Requires-Dist: redditcleaner
Requires-Dist: contractions
Requires-Dist: nltk
Requires-Dist: spacy
Requires-Dist: tqdm
Requires-Dist: pandas
Requires-Dist: praw>=7.7
Requires-Dist: numpy
Requires-Dist: convokit>=3.1.0
Dynamic: author
Dynamic: author-email
Dynamic: classifier
Dynamic: description
Dynamic: description-content-type
Dynamic: home-page
Dynamic: license
Dynamic: requires-dist
Dynamic: requires-python
Dynamic: summary
